stripe_subscription/__init__.py
stripe_subscription/admin.py
stripe_subscription/apps.py
stripe_subscription/forms.py
stripe_subscription/models.py
stripe_subscription/tests.py
stripe_subscription/urls.py
stripe_subscription/utils.py
stripe_subscription/views.py
stripe_subscription/migrations/0001_initial.py
stripe_subscription/migrations/0002_auto_20210319_0226.py
stripe_subscription/migrations/0003_trial_days.py
stripe_subscription/migrations/0004_alter_plan_price.py
stripe_subscription/migrations/0005_auto_20210825_1832.py
stripe_subscription/migrations/__init__.py
stripe_subscription/static/.DS_Store
stripe_subscription/static/stripe_subscription/.DS_Store
stripe_subscription/static/stripe_subscription/images/.DS_Store
stripe_subscription/static/stripe_subscription/images/apple-pay.svg
stripe_subscription/static/stripe_subscription/images/cards/.DS_Store
stripe_subscription/static/stripe_subscription/images/cards/2co.png
stripe_subscription/static/stripe_subscription/images/cards/alipay.png
stripe_subscription/static/stripe_subscription/images/cards/amazon.png
stripe_subscription/static/stripe_subscription/images/cards/american_express.png
stripe_subscription/static/stripe_subscription/images/cards/american_express_black.png
stripe_subscription/static/stripe_subscription/images/cards/american_express_green.png
stripe_subscription/static/stripe_subscription/images/cards/american_express_platinum.png
stripe_subscription/static/stripe_subscription/images/cards/asiapay.png
stripe_subscription/static/stripe_subscription/images/cards/bank_of_america.png
stripe_subscription/static/stripe_subscription/images/cards/cashu.png
stripe_subscription/static/stripe_subscription/images/cards/chase.png
stripe_subscription/static/stripe_subscription/images/cards/china_union.png
stripe_subscription/static/stripe_subscription/images/cards/cirrus.png
stripe_subscription/static/stripe_subscription/images/cards/credit_card.png
django_stripe_subscription-0.0.37.dist-info/METADATA
django_stripe_subscription-0.0.37.dist-info/WHEEL
django_stripe_subscription-0.0.37.dist-info/top_level.txt
django_stripe_subscription-0.0.37.dist-info/zip-safe
django_stripe_subscription-0.0.37.dist-info/RECORD
