Metadata-Version: 2.1
Name: django-stripe-subscription
Version: 0.0.37
Summary: Stripe Subscription API client
Home-page: https://github.com/python33/django-stripe-subscription
Author: Petr Dovnar
Author-email: petrdovnar@gmail.com
License: BSD
Project-URL: Source, https://github.com/python33/django-stripe-subscription
Platform: UNKNOWN
Classifier: Development Status :: 5 - Production/Stable
Classifier: Environment :: Web Environment
Classifier: Framework :: Django
Classifier: Framework :: Django :: 2.0
Classifier: Framework :: Django :: 3.0
Classifier: Intended Audience :: Developers
Classifier: License :: OSI Approved :: BSD License
Classifier: Operating System :: OS Independent
Classifier: Programming Language :: Python
Classifier: Programming Language :: Python :: 3
Requires-Python: >=3.0
Requires-Dist: django (>=2.0)
Requires-Dist: stripe (>=2.54.0)
